{
  "repository": "openclaw/openclaw",
  "generatedAt": "2026-07-24T15:42:42.599Z",
  "snapshots": [
    {
      "capturedOn": "2026-03-01",
      "capturedAt": "2026-03-01T00:00:00.000Z",
      "issueOpen": 6480,
      "issueClosed": 10686,
      "prOpen": 5493,
      "prClosed": 17907,
      "workflowRuns": 521903,
      "source": "manual-post",
      "approximateDate": true
    },
    {
      "capturedOn": "2026-06-14",
      "capturedAt": "2026-06-14T00:00:00.000Z",
      "issueOpen": 3934,
      "issueClosed": 35875,
      "prOpen": 3611,
      "prClosed": 47253,
      "workflowRuns": null,
      "source": "manual-post",
      "approximateDate": false
    },
    {
      "capturedOn": "2026-07-12",
      "capturedAt": "2026-07-12T23:08:27.915Z",
      "issueOpen": 3675,
      "issueClosed": 39308,
      "prOpen": 2792,
      "prClosed": 57607,
      "workflowRuns": 40000,
      "source": "github-actions",
      "approximateDate": false
    },
    {
      "capturedOn": "2026-07-13",
      "capturedAt": "2026-07-13T23:11:39.036Z",
      "issueOpen": 3813,
      "issueClosed": 39555,
      "prOpen": 2741,
      "prClosed": 58348,
      "workflowRuns": 40000,
      "source": "github-actions",
      "approximateDate": false
    },
    {
      "capturedOn": "2026-07-14",
      "capturedAt": "2026-07-14T23:10:25.343Z",
      "issueOpen": 3855,
      "issueClosed": 39740,
      "prOpen": 2799,
      "prClosed": 58981,
      "workflowRuns": 40000,
      "source": "github-actions",
      "approximateDate": false
    },
    {
      "capturedOn": "2026-07-15",
      "capturedAt": "2026-07-15T23:11:35.529Z",
      "issueOpen": 3885,
      "issueClosed": 39854,
      "prOpen": 2874,
      "prClosed": 59424,
      "workflowRuns": 40000,
      "source": "github-actions",
      "approximateDate": false
    },
    {
      "capturedOn": "2026-07-16",
      "capturedAt": "2026-07-16T22:15:28.852Z",
      "issueOpen": 3868,
      "issueClosed": 40038,
      "prOpen": 2896,
      "prClosed": 60154,
      "workflowRuns": 40000,
      "source": "github-actions",
      "approximateDate": false
    },
    {
      "capturedOn": "2026-07-17",
      "capturedAt": "2026-07-17T23:06:59.208Z",
      "issueOpen": 3881,
      "issueClosed": 40147,
      "prOpen": 3026,
      "prClosed": 60817,
      "workflowRuns": 40000,
      "source": "github-actions",
      "approximateDate": false
    },
    {
      "capturedOn": "2026-07-18",
      "capturedAt": "2026-07-18T23:09:19.486Z",
      "issueOpen": 3898,
      "issueClosed": 40242,
      "prOpen": 2970,
      "prClosed": 61556,
      "workflowRuns": 40000,
      "source": "github-actions",
      "approximateDate": false
    },
    {
      "capturedOn": "2026-07-19",
      "capturedAt": "2026-07-19T23:10:04.485Z",
      "issueOpen": 3912,
      "issueClosed": 40321,
      "prOpen": 2993,
      "prClosed": 61991,
      "workflowRuns": 40000,
      "source": "github-actions",
      "approximateDate": false
    },
    {
      "capturedOn": "2026-07-20",
      "capturedAt": "2026-07-20T23:13:47.036Z",
      "issueOpen": 3952,
      "issueClosed": 40389,
      "prOpen": 3083,
      "prClosed": 62180,
      "workflowRuns": 40000,
      "source": "github-actions",
      "approximateDate": false
    },
    {
      "capturedOn": "2026-07-21",
      "capturedAt": "2026-07-21T23:10:31.020Z",
      "issueOpen": 3980,
      "issueClosed": 40551,
      "prOpen": 3041,
      "prClosed": 62453,
      "workflowRuns": 40000,
      "source": "github-actions",
      "approximateDate": false
    },
    {
      "capturedOn": "2026-07-22",
      "capturedAt": "2026-07-22T18:20:41.454Z",
      "issueOpen": 3973,
      "issueClosed": 40644,
      "prOpen": 2973,
      "prClosed": 62714,
      "workflowRuns": 40000,
      "source": "github-actions",
      "approximateDate": false
    },
    {
      "capturedOn": "2026-07-23",
      "capturedAt": "2026-07-23T23:10:58.020Z",
      "issueOpen": 4040,
      "issueClosed": 40692,
      "prOpen": 2927,
      "prClosed": 63104,
      "workflowRuns": 40000,
      "source": "github-actions",
      "approximateDate": false
    },
    {
      "capturedOn": "2026-07-24",
      "capturedAt": "2026-07-24T15:42:42.599Z",
      "issueOpen": 4068,
      "issueClosed": 40719,
      "prOpen": 2901,
      "prClosed": 63258,
      "workflowRuns": 40000,
      "source": "github-actions",
      "approximateDate": false
    }
  ],
  "activity": {
    "issues": [
      {
        "kind": "issue",
        "number": 92186,
        "title": "Foreground reply fence (automatic mode) cancels delivery of completed replies to earlier concurrent group messages — reply shown in dashboard, never delivered to WhatsApp",
        "url": "https://github.com/openclaw/openclaw/issues/92186",
        "state": "open",
        "author": "Mohd-Mursaleen",
        "updatedAt": "2026-07-24T15:35:46Z"
      },
      {
        "kind": "issue",
        "number": 8673,
        "title": "Add retry logic to OAuth token refresh",
        "url": "https://github.com/openclaw/openclaw/issues/8673",
        "state": "open",
        "author": "skyblue-will",
        "updatedAt": "2026-07-24T15:33:35Z"
      },
      {
        "kind": "issue",
        "number": 113353,
        "title": "[Feature]: Use Codex OAuth for browser realtime Talk",
        "url": "https://github.com/openclaw/openclaw/issues/113353",
        "state": "open",
        "author": "Solvely-Colin",
        "updatedAt": "2026-07-24T15:32:47Z"
      },
      {
        "kind": "issue",
        "number": 113314,
        "title": "[Bug]: external PR CI: system-agent TUI-shell test times out (120s) on GitHub-hosted runners",
        "url": "https://github.com/openclaw/openclaw/issues/113314",
        "state": "open",
        "author": "aspalagin",
        "updatedAt": "2026-07-24T15:30:05Z"
      }
    ],
    "prs": [
      {
        "kind": "pr",
        "number": 113104,
        "title": "build(deps): bump the actions group across 1 directory with 5 updates",
        "url": "https://github.com/openclaw/openclaw/pull/113104",
        "state": "open",
        "author": "dependabot[bot]",
        "updatedAt": "2026-07-24T15:42:34Z"
      },
      {
        "kind": "pr",
        "number": 102117,
        "title": "fix(core): surface non_deliverable_terminal_turn as outbound fallback to channel plugins",
        "url": "https://github.com/openclaw/openclaw/pull/102117",
        "state": "open",
        "author": "dolphinsboy",
        "updatedAt": "2026-07-24T15:41:03Z"
      },
      {
        "kind": "pr",
        "number": 113352,
        "title": "fix(reply): converge concurrent new-session dispatches onto one sessionId",
        "url": "https://github.com/openclaw/openclaw/pull/113352",
        "state": "open",
        "author": "timon0305",
        "updatedAt": "2026-07-24T15:40:17Z"
      },
      {
        "kind": "pr",
        "number": 113340,
        "title": "fix(acp): don't abort spawn on session label collision",
        "url": "https://github.com/openclaw/openclaw/pull/113340",
        "state": "open",
        "author": "timon0305",
        "updatedAt": "2026-07-24T15:39:57Z"
      },
      {
        "kind": "pr",
        "number": 112589,
        "title": "feat: add lease-bound metadata to session spawns",
        "url": "https://github.com/openclaw/openclaw/pull/112589",
        "state": "open",
        "author": "yuzuqiang",
        "updatedAt": "2026-07-24T15:42:39Z"
      },
      {
        "kind": "pr",
        "number": 112702,
        "title": "fix(auto-reply): match throttling transient errors in fallback-state regex",
        "url": "https://github.com/openclaw/openclaw/pull/112702",
        "state": "open",
        "author": "yangxiansheng",
        "updatedAt": "2026-07-24T15:39:28Z"
      }
    ]
  }
}
